saltext/elasticsearch8/__init__.py
saltext/elasticsearch8/loader.py
saltext/elasticsearch8/version.py
saltext/elasticsearch8/modules/__init__.py
saltext/elasticsearch8/modules/elasticsearch8_mod.py
saltext/elasticsearch8/returners/__init__.py
saltext/elasticsearch8/returners/elasticsearch8_mod.py
saltext/elasticsearch8/states/__init__.py
saltext/elasticsearch8/states/elasticsearch8_mod.py
saltext.elasticsearch8-1.0.12.dist-info/LICENSE
saltext.elasticsearch8-1.0.12.dist-info/LICENSE.new
saltext.elasticsearch8-1.0.12.dist-info/METADATA
saltext.elasticsearch8-1.0.12.dist-info/WHEEL
saltext.elasticsearch8-1.0.12.dist-info/entry_points.txt
saltext.elasticsearch8-1.0.12.dist-info/top_level.txt
saltext.elasticsearch8-1.0.12.dist-info/RECORD
